streamly.py
Streamly-0.3.dist-info/METADATA
Streamly-0.3.dist-info/RECORD
Streamly-0.3.dist-info/WHEEL
Streamly-0.3.dist-info/top_level.txt
