Metadata-Version: 2.1
Name: Streamly
Version: 0.3
Summary: Streamly is a very simple yet powerful wrapper for streams.
Home-page: https://github.com/adamcunnington/Streamly
Author: Adam Cunnington
Author-email: adamcunnington.info@gmail.com
License: MIT
Project-URL: Documentation, https://streamly.readthedocs.io
Platform: UNKNOWN
Classifier: Development Status :: 4 - Beta
Classifier: Intended Audience :: Developers
Classifier: License :: OSI Approved :: MIT License
Classifier: Operating System :: OS Independent
Classifier: Programming Language :: Python :: 3 :: Only
Requires-Python: >=3.1
